LICENSE
MANIFEST.in
README.md
scrapy.cfg
setup.cfg
setup.py
os_scrapy_aio_resolver/__init__.py
os_scrapy_aio_resolver/items.py
os_scrapy_aio_resolver/middlewares.py
os_scrapy_aio_resolver/pipelines.py
os_scrapy_aio_resolver/resolver.py
os_scrapy_aio_resolver/settings.py
os_scrapy_aio_resolver.egg-info/PKG-INFO
os_scrapy_aio_resolver.egg-info/SOURCES.txt
os_scrapy_aio_resolver.egg-info/dependency_links.txt
os_scrapy_aio_resolver.egg-info/not-zip-safe
os_scrapy_aio_resolver.egg-info/requires.txt
os_scrapy_aio_resolver.egg-info/top_level.txt
os_scrapy_aio_resolver/spiders/__init__.py
requirements/requirements-lint.txt
requirements/requirements-test.txt
requirements/requirements.txt
tests/__init__.py
tests/test_scrapy_check.py